{
  "type": "minecraft:archaeology",
  "pools": [
    {
      "rolls": 1,
      "bonus_rolls": 0,
      "entries": [
        {
          "type": "minecraft:item",
          "name": "minecraft:dead_bush",
          "weight": 4
        },
        {
          "type": "minecraft:item",
          "name": "minecraft:clay_ball",
          "weight": 4
        },
        {
          "type": "minecraft:item",
          "name": "minecraft:amethyst_shard",
          "weight": 4
        },
        {
          "type": "minecraft:item",
          "name": "minecraft:glass_bottle",
          "weight": 4
        },
        {
          "type": "minecraft:item",
          "name": "minecraft:diamond",
          "weight": 3
        },
        {
          "type": "minecraft:item",
          "name": "minecraft:prismarine_shard",
          "weight": 3
        },
        {
          "type": "minecraft:item",
          "name": "minecraft:arrow",
          "weight": 3
        },
        {
          "type": "minecraft:item",
          "name": "minecraft:iron_sword",
          "weight": 3,
          "functions": [
            {
              "function": "minecraft:set_damage",
              "damage": {
                "min": 0.2,
                "max": 0.5
              }
            }
          ]
        },
        {
          "type": "minecraft:item",
          "name": "minecraft:bow",
          "weight": 3,
          "functions": [
            {
              "function": "minecraft:set_damage",
              "damage": {
                "min": 0.2,
                "max": 0.5
              }
            }
          ]
        },
        {
          "type": "minecraft:loot_table",
          "name": "mythic_charms:archaeology/composer/pattern/silver_composer",
          "weight": 2
        },
        {
          "type": "minecraft:item",
          "name": "minecraft:blaze_rod"
        }
      ]
    }
  ]
}