{
  "name": "Echoing W. & Blazing E.",
  "icon": "mythic_charms:textures/echoing_wrath_and_battle_fury.png",
  "category": "mythic_charms:combinations_category",
  "advancement": "mythic_charms:book/combinations/echoing_wrath_and_battle_fury",
  "sortnum": 1,
  "pages": [
    {
      "type": "patchouli:text",
      "text": " When combining $(l:mythic_charms:charms/charm_of_echoing_wrath_entry)Echoing Wrath$() and $(l:mythic_charms:charms/charm_of_blazing_embrace_entry)Blazing Embrace$(), sets surrounding entities on fire, but the echo damage is decreased by half."
    }
  ]
}